[{"title":"Action & Adventure","link":"https://netflix.com/browse/genre/1365","genre":"action & adventure"},{"title":"Asian Action Movies","link":"https://netflix.com/browse/genre/77232","genre":"action & adventure"},{"title":"Classic Action & Adventure","link":"https://netflix.com/browse/genre/46576","genre":"action & adventure"},{"title":"Action Comedies","link":"https://netflix.com/browse/genre/43040","genre":"action & adventure"},{"title":"Action Thrillers","link":"https://netflix.com/browse/genre/43048","genre":"action & adventure"},{"title":"Martial Arts Movies","link":"https://netflix.com/browse/genre/8985","genre":"action & adventure"},{"title":"Military Action & Adventure","link":"https://netflix.com/browse/genre/2125","genre":"action & adventure"},{"title":"Adventures","link":"https://netflix.com/browse/genre/7442","genre":"action & adventure"},{"title":"Comic Book and Superhero Movies","link":"https://netflix.com/browse/genre/10118","genre":"action & adventure"},{"title":"Westerns","link":"https://netflix.com/browse/genre/7700","genre":"action & adventure"},{"title":"Spy Action & Adventure","link":"https://netflix.com/browse/genre/10702","genre":"action & adventure"},{"title":"Crime Action & Adventure","link":"https://netflix.com/browse/genre/9584","genre":"action & adventure"},{"title":"Foreign Action & Adventure","link":"https://netflix.com/browse/genre/11828","genre":"action & adventure"},{"title":"Anime","link":"https://netflix.com/browse/genre/7424","genre":"anime"},{"title":"Adult Animation","link":"https://netflix.com/browse/genre/11881","genre":"anime"},{"title":"Anime Action","link":"https://netflix.com/browse/genre/2653","genre":"anime"},{"title":"Anime Comedies","link":"https://netflix.com/browse/genre/9302","genre":"anime"},{"title":"Anime Dramas","link":"https://netflix.com/browse/genre/452","genre":"anime"},{"title":"Anime Features","link":"https://netflix.com/browse/genre/3063","genre":"anime"},{"title":"Anime Sci-Fi","link":"https://netflix.com/browse/genre/2729","genre":"anime"},{"title":"Anime Horror","link":"https://netflix.com/browse/genre/10695","genre":"anime"},{"title":"Anime Fantasy","link":"https://netflix.com/browse/genre/11146","genre":"anime"},{"title":"Anime Series","link":"https://netflix.com/browse/genre/6721","genre":"anime"},{"title":"Children & Family Movies","link":"https://netflix.com/browse/genre/783","genre":"children & family"},{"title":"Movies for ages 0 to 2","link":"https://netflix.com/browse/genre/6796","genre":"children & family"},{"title":"Movies for ages 2 to 4","link":"https://netflix.com/browse/genre/6218","genre":"children & family"},{"title":"Movies for ages 5 to 7","link":"https://netflix.com/browse/genre/5455","genre":"children & family"},{"title":"Movies for ages 8 to 10","link":"https://netflix.com/browse/genre/561","genre":"children & family"},{"title":"Movies for ages 11 to 12","link":"https://netflix.com/browse/genre/6962","genre":"children & family"},{"title":"Education for Kids","link":"https://netflix.com/browse/genre/10659","genre":"children & family"},{"title":"Disney","link":"https://netflix.com/browse/genre/67673","genre":"children & family"},{"title":"Movies based on children’s books","link":"https://netflix.com/browse/genre/10056","genre":"children & family"},{"title":"Family Features","link":"https://netflix.com/browse/genre/51056","genre":"children & family"},{"title":"TV Cartoons","link":"https://netflix.com/browse/genre/11177","genre":"children & family"},{"title":"Kids’ TV","link":"https://netflix.com/browse/genre/27346","genre":"children & family"},{"title":"Kids Music","link":"https://netflix.com/browse/genre/52843","genre":"children & family"},{"title":"Animal Tales","link":"https://netflix.com/browse/genre/5507","genre":"children & family"},{"title":"Classic Movies","link":"https://netflix.com/browse/genre/31574","genre":"classic movies"},{"title":"Classic Comedies","link":"https://netflix.com/browse/genre/31694","genre":"classic movies"},{"title":"Classic Dramas","link":"https://netflix.com/browse/genre/29809","genre":"classic movies"},{"title":"Classic Sci-Fi & Fantasy","link":"https://netflix.com/browse/genre/47147","genre":"classic movies"},{"title":"Classic Thrillers","link":"https://netflix.com/browse/genre/46588","genre":"classic movies"},{"title":"Film Noir","link":"https://netflix.com/browse/genre/7687","genre":"classic movies"},{"title":"Classic War Movies","link":"https://netflix.com/browse/genre/48744","genre":"classic movies"},{"title":"Epics","link":"https://netflix.com/browse/genre/52858","genre":"classic movies"},{"title":"Classic Foreign Movies","link":"https://netflix.com/browse/genre/32473","genre":"classic movies"},{"title":"Silent Movies","link":"https://netflix.com/browse/genre/53310","genre":"classic movies"},{"title":"Classic Westerns","link":"https://netflix.com/browse/genre/47465","genre":"classic movies"},{"title":"Comedies","link":"https://netflix.com/browse/genre/6548","genre":"comedy"},{"title":"Dark Comedies","link":"https://netflix.com/browse/genre/869","genre":"comedy"},{"title":"Foreign Comedies","link":"https://netflix.com/browse/genre/4426","genre":"comedy"},{"title":"Late Night Comedies","link":"https://netflix.com/browse/genre/1402","genre":"comedy"},{"title":"Mockumentaries","link":"https://netflix.com/browse/genre/26","genre":"comedy"},{"title":"Political Comedies","link":"https://netflix.com/browse/genre/2700","genre":"comedy"},{"title":"Screwball Comedies","link":"https://netflix.com/browse/genre/9702","genre":"comedy"},{"title":"Sports Comedies","link":"https://netflix.com/browse/genre/5286","genre":"comedy"},{"title":"Stand-up Comedy","link":"https://netflix.com/browse/genre/11559","genre":"comedy"},{"title":"Teen Comedies","link":"https://netflix.com/browse/genre/3519","genre":"comedy"},{"title":"Satires","link":"https://netflix.com/browse/genre/4922","genre":"comedy"},{"title":"Romantic Comedies","link":"https://netflix.com/browse/genre/5475","genre":"comedy"},{"title":"Slapstick Comedies","link":"https://netflix.com/browse/genre/10256","genre":"comedy"},{"title":"Cult Movies","link":"https://netflix.com/browse/genre/7627","genre":"comedy"},{"title":"B-Horror Movies","link":"https://netflix.com/browse/genre/8195","genre":"comedy"},{"title":"Campy Movies","link":"https://netflix.com/browse/genre/1252","genre":"comedy"},{"title":"Cult Horror Movies","link":"https://netflix.com/browse/genre/10944","genre":"comedy"},{"title":"Cult Sci-Fi & Fantasy","link":"https://netflix.com/browse/genre/4734","genre":"comedy"},{"title":"Cult Comedies","link":"https://netflix.com/browse/genre/9434","genre":"comedy"},{"title":"Independent Comedies","link":"https://netflix.com/browse/genre/4195","genre":"comedy"},{"title":"Documentaries","link":"https://netflix.com/browse/genre/6839","genre":"documentary"},{"title":"Biographical Documentaries","link":"https://netflix.com/browse/genre/3652","genre":"documentary"},{"title":"Crime Documentaries","link":"https://netflix.com/browse/genre/9875","genre":"documentary"},{"title":"Foreign Documentaries","link":"https://netflix.com/browse/genre/5161","genre":"documentary"},{"title":"Historical Documentaries","link":"https://netflix.com/browse/genre/5349","genre":"documentary"},{"title":"Military Documentaries","link":"https://netflix.com/browse/genre/4006","genre":"documentary"},{"title":"Sports Documentaries","link":"https://netflix.com/browse/genre/180","genre":"documentary"},{"title":"Music & Concert Documentaries","link":"https://netflix.com/browse/genre/90361","genre":"documentary"},{"title":"Travel & Adventure Documentaries","link":"https://netflix.com/browse/genre/1159","genre":"documentary"},{"title":"Political Documentaries","link":"https://netflix.com/browse/genre/7018","genre":"documentary"},{"title":"Religious Documentaries","link":"https://netflix.com/browse/genre/10005","genre":"documentary"},{"title":"Science & Nature Documentaries","link":"https://netflix.com/browse/genre/2595","genre":"documentary"},{"title":"Social & Cultural Documentaries","link":"https://netflix.com/browse/genre/3675","genre":"documentary"},{"title":"Foreign Movies","link":"https://netflix.com/browse/genre/7462","genre":"drama"},{"title":"Art House Movies","link":"https://netflix.com/browse/genre/29764","genre":"drama"},{"title":"Foreign Action & Adventure","link":"https://netflix.com/browse/genre/11828","genre":"drama"},{"title":"Classic Foreign Movies","link":"https://netflix.com/browse/genre/32473","genre":"drama"},{"title":"Foreign Comedies","link":"https://netflix.com/browse/genre/4426","genre":"drama"},{"title":"Foreign Documentaries","link":"https://netflix.com/browse/genre/5161","genre":"drama"},{"title":"Foreign Dramas","link":"https://netflix.com/browse/genre/2150","genre":"drama"},{"title":"Foreign Gay & Lesbian Movies","link":"https://netflix.com/browse/genre/8243","genre":"drama"},{"title":"Foreign Horror Movies","link":"https://netflix.com/browse/genre/8654","genre":"drama"},{"title":"Foreign Sci-Fi & Fantasy","link":"https://netflix.com/browse/genre/6485","genre":"drama"},{"title":"Foreign Thrillers","link":"https://netflix.com/browse/genre/10306","genre":"drama"},{"title":"Romantic Foreign Movies","link":"https://netflix.com/browse/genre/7153","genre":"drama"},{"title":"African Movies","link":"https://netflix.com/browse/genre/3761","genre":"drama"},{"title":"Australian Movies","link":"https://netflix.com/browse/genre/5230","genre":"drama"},{"title":"Belgian Movies","link":"https://netflix.com/browse/genre/262","genre":"drama"},{"title":"Korean Movies","link":"https://netflix.com/browse/genre/5685","genre":"drama"},{"title":"Latin American Movies","link":"https://netflix.com/browse/genre/1613","genre":"drama"},{"title":"Middle Eastern Movies","link":"https://netflix.com/browse/genre/5875","genre":"drama"},{"title":"New Zealand Movies","link":"https://netflix.com/browse/genre/63782","genre":"drama"},{"title":"Russian","link":"https://netflix.com/browse/genre/11567","genre":"drama"},{"title":"Scandinavian Movies","link":"https://netflix.com/browse/genre/9292","genre":"drama"},{"title":"Southeast Asian Movies","link":"https://netflix.com/browse/genre/9196","genre":"drama"},{"title":"Spanish Movies","link":"https://netflix.com/browse/genre/58741","genre":"drama"},{"title":"Greek Movies","link":"https://netflix.com/browse/genre/61115","genre":"drama"},{"title":"German Movies","link":"https://netflix.com/browse/genre/58886","genre":"drama"},{"title":"French Movies","link":"https://netflix.com/browse/genre/58807","genre":"drama"},{"title":"Eastern European Movies","link":"https://netflix.com/browse/genre/5254","genre":"drama"},{"title":"Dutch Movies","link":"https://netflix.com/browse/genre/10606","genre":"drama"},{"title":"Irish Movies","link":"https://netflix.com/browse/genre/58750","genre":"drama"},{"title":"Japanese Movies","link":"https://netflix.com/browse/genre/10398","genre":"drama"},{"title":"Italian Movies","link":"https://netflix.com/browse/genre/8221","genre":"drama"},{"title":"Indian Movies","link":"https://netflix.com/browse/genre/10463","genre":"drama"},{"title":"Chinese Movies","link":"https://netflix.com/browse/genre/3960","genre":"drama"},{"title":"British Movies","link":"https://netflix.com/browse/genre/10757","genre":"drama"},{"title":"Horror Movies","link":"https://netflix.com/browse/genre/8711","genre":"horror movies"},{"title":"B-Horror Movies","link":"https://netflix.com/browse/genre/8195","genre":"horror movies"},{"title":"Creature Features","link":"https://netflix.com/browse/genre/6895","genre":"horror movies"},{"title":"Cult Horror Movies","link":"https://netflix.com/browse/genre/10944","genre":"horror movies"},{"title":"Deep Sea Horror Movies","link":"https://netflix.com/browse/genre/45028","genre":"horror movies"},{"title":"Foreign Horror Movies","link":"https://netflix.com/browse/genre/8654","genre":"horror movies"},{"title":"Horror Comedy","link":"https://netflix.com/browse/genre/89585","genre":"horror movies"},{"title":"Monster Movies","link":"https://netflix.com/browse/genre/947","genre":"horror movies"},{"title":"Slasher and Serial Killer Movies","link":"https://netflix.com/browse/genre/8646","genre":"horror movies"},{"title":"Supernatural Horror Movies","link":"https://netflix.com/browse/genre/42023","genre":"horror movies"},{"title":"Teen Screams","link":"https://netflix.com/browse/genre/52147","genre":"horror movies"},{"title":"Vampire Horror Movies","link":"https://netflix.com/browse/genre/75804","genre":"horror movies"},{"title":"Werewolf Horror Movies","link":"https://netflix.com/browse/genre/75930","genre":"horror movies"},{"title":"Zombie Horror Movies","link":"https://netflix.com/browse/genre/75405","genre":"horror movies"},{"title":"Satanic Stories","link":"https://netflix.com/browse/genre/6998","genre":"horror movies"},{"title":"Independent Movies","link":"https://netflix.com/browse/genre/7077","genre":"horror movies"},{"title":"Experimental Movies","link":"https://netflix.com/browse/genre/11079","genre":"horror movies"},{"title":"Independent Action & Adventure","link":"https://netflix.com/browse/genre/11804","genre":"horror movies"},{"title":"Independent Thrillers","link":"https://netflix.com/browse/genre/3269","genre":"horror movies"},{"title":"Music","link":"https://netflix.com/browse/genre/1701","genre":"musical"},{"title":"Kids Music","link":"https://netflix.com/browse/genre/52843","genre":"musical"},{"title":"Country & Western/Folk","link":"https://netflix.com/browse/genre/1105","genre":"musical"},{"title":"Jazz & Easy Listening","link":"https://netflix.com/browse/genre/10271","genre":"musical"},{"title":"Latin Music","link":"https://netflix.com/browse/genre/10741","genre":"musical"},{"title":"Urban & Dance Concerts","link":"https://netflix.com/browse/genre/9472","genre":"musical"},{"title":"World Music Concerts","link":"https://netflix.com/browse/genre/2856","genre":"musical"},{"title":"Rock & Pop Concerts","link":"https://netflix.com/browse/genre/3278","genre":"musical"},{"title":"Musicals","link":"https://netflix.com/browse/genre/13335","genre":"musical"},{"title":"Classic Musicals","link":"https://netflix.com/browse/genre/32392","genre":"musical"},{"title":"Disney Musicals","link":"https://netflix.com/browse/genre/59433","genre":"musical"},{"title":"Showbiz Musicals","link":"https://netflix.com/browse/genre/13573","genre":"musical"},{"title":"Stage Musicals","link":"https://netflix.com/browse/genre/55774","genre":"musical"},{"title":"Romantic Movies","link":"https://netflix.com/browse/genre/8883","genre":"romance"},{"title":"Romantic Favorites","link":"https://netflix.com/browse/genre/502675","genre":"romance"},{"title":"Quirky Romance","link":"https://netflix.com/browse/genre/36103","genre":"romance"},{"title":"Romantic Independent Movies","link":"https://netflix.com/browse/genre/9916","genre":"romance"},{"title":"Romantic Foreign Movies","link":"https://netflix.com/browse/genre/7153","genre":"romance"},{"title":"Romantic Dramas","link":"https://netflix.com/browse/genre/1255","genre":"romance"},{"title":"Steamy Romantic Movies","link":"https://netflix.com/browse/genre/35800","genre":"romance"},{"title":"Classic Romantic Movies","link":"https://netflix.com/browse/genre/31273","genre":"romance"},{"title":"Romantic Comedies","link":"https://netflix.com/browse/genre/5475","genre":"romance"},{"title":"Sci-Fi & Fantasy","link":"https://netflix.com/browse/genre/1492","genre":"sci-fi & fantasy"},{"title":"Action Sci-Fi & Fantasy","link":"https://netflix.com/browse/genre/1568","genre":"sci-fi & fantasy"},{"title":"Alien Sci-Fi","link":"https://netflix.com/browse/genre/3327","genre":"sci-fi & fantasy"},{"title":"Classic Sci-Fi & Fantasy","link":"https://netflix.com/browse/genre/47147","genre":"sci-fi & fantasy"},{"title":"Cult Sci-Fi & Fantasy","link":"https://netflix.com/browse/genre/4734","genre":"sci-fi & fantasy"},{"title":"Fantasy Movies","link":"https://netflix.com/browse/genre/9744","genre":"sci-fi & fantasy"},{"title":"Sci-Fi Adventure","link":"https://netflix.com/browse/genre/6926","genre":"sci-fi & fantasy"},{"title":"Sci-Fi Dramas","link":"https://netflix.com/browse/genre/3916","genre":"sci-fi & fantasy"},{"title":"Sci-Fi Horror Movies","link":"https://netflix.com/browse/genre/1694","genre":"sci-fi & fantasy"},{"title":"Sci-Fi Thrillers","link":"https://netflix.com/browse/genre/11014","genre":"sci-fi & fantasy"},{"title":"Foreign Sci-Fi & Fantasy","link":"https://netflix.com/browse/genre/6485","genre":"sci-fi & fantasy"},{"title":"Sports Movies","link":"https://netflix.com/browse/genre/4370","genre":"sports"},{"title":"Sports Comedies","link":"https://netflix.com/browse/genre/5286","genre":"sports"},{"title":"Sports Documentaries","link":"https://netflix.com/browse/genre/180","genre":"sports"},{"title":"Sports Dramas","link":"https://netflix.com/browse/genre/7243","genre":"sports"},{"title":"Baseball Movies","link":"https://netflix.com/browse/genre/12339","genre":"sports"},{"title":"Football Movies","link":"https://netflix.com/browse/genre/12803","genre":"sports"},{"title":"Boxing Movies","link":"https://netflix.com/browse/genre/12443","genre":"sports"},{"title":"Soccer Movies","link":"https://netflix.com/browse/genre/12549","genre":"sports"},{"title":"Martial Arts, Boxing & Wrestling","link":"https://netflix.com/browse/genre/6695","genre":"sports"},{"title":"Basketball Movies","link":"https://netflix.com/browse/genre/12762","genre":"sports"},{"title":"Sports & Fitness","link":"https://netflix.com/browse/genre/9327","genre":"sports"},{"title":"Thrillers","link":"https://netflix.com/browse/genre/8933","genre":"thrillers"},{"title":"Action Thrillers","link":"https://netflix.com/browse/genre/43048","genre":"thrillers"},{"title":"Classic Thrillers","link":"https://netflix.com/browse/genre/46588","genre":"thrillers"},{"title":"Crime Thrillers","link":"https://netflix.com/browse/genre/10499","genre":"thrillers"},{"title":"Foreign Thrillers","link":"https://netflix.com/browse/genre/10306","genre":"thrillers"},{"title":"Independent Thrillers","link":"https://netflix.com/browse/genre/3269","genre":"thrillers"},{"title":"Gangster Movies","link":"https://netflix.com/browse/genre/31851","genre":"thrillers"},{"title":"Psychological Thrillers","link":"https://netflix.com/browse/genre/5505","genre":"thrillers"},{"title":"Political Thrillers","link":"https://netflix.com/browse/genre/10504","genre":"thrillers"},{"title":"Mysteries","link":"https://netflix.com/browse/genre/9994","genre":"thrillers"},{"title":"Sci-Fi Thrillers","link":"https://netflix.com/browse/genre/11014","genre":"thrillers"},{"title":"Spy Thrillers","link":"https://netflix.com/browse/genre/9147","genre":"thrillers"},{"title":"Steamy Thrillers","link":"https://netflix.com/browse/genre/972","genre":"thrillers"},{"title":"Supernatural Thrillers","link":"https://netflix.com/browse/genre/11140","genre":"thrillers"},{"title":"TV Shows","link":"https://netflix.com/browse/genre/83","genre":"tv & shows"},{"title":"British TV Shows","link":"https://netflix.com/browse/genre/52117","genre":"tv & shows"},{"title":"Classic TV Shows","link":"https://netflix.com/browse/genre/46553","genre":"tv & shows"},{"title":"Crime TV Shows","link":"https://netflix.com/browse/genre/26146","genre":"tv & shows"},{"title":"Cult TV Shows","link":"https://netflix.com/browse/genre/74652","genre":"tv & shows"},{"title":"Food & Travel TV","link":"https://netflix.com/browse/genre/72436","genre":"tv & shows"},{"title":"Kids’ TV","link":"https://netflix.com/browse/genre/27346","genre":"tv & shows"},{"title":"Korean TV Shows","link":"https://netflix.com/browse/genre/67879","genre":"tv & shows"},{"title":"Miniseries","link":"https://netflix.com/browse/genre/4814","genre":"tv & shows"},{"title":"Military TV Shows","link":"https://netflix.com/browse/genre/25804","genre":"tv & shows"},{"title":"Science & Nature TV","link":"https://netflix.com/browse/genre/52780","genre":"tv & shows"},{"title":"TV Action & Adventure","link":"https://netflix.com/browse/genre/10673","genre":"tv & shows"},{"title":"TV Comedies","link":"https://netflix.com/browse/genre/10375","genre":"tv & shows"},{"title":"TV Documentaries","link":"https://netflix.com/browse/genre/10105","genre":"tv & shows"},{"title":"TV Dramas","link":"https://netflix.com/browse/genre/11714","genre":"tv & shows"},{"title":"TV Horror","link":"https://netflix.com/browse/genre/83059","genre":"tv & shows"},{"title":"TV Mysteries","link":"https://netflix.com/browse/genre/4366","genre":"tv & shows"},{"title":"TV Sci-Fi & Fantasy","link":"https://netflix.com/browse/genre/1372","genre":"tv & shows"},{"title":"Reality TV","link":"https://netflix.com/browse/genre/9833","genre":"tv & shows"},{"title":"Teen TV Shows","link":"https://netflix.com/browse/genre/60951","genre":"tv & shows"}]